pysf/__init__.py
pysf/data.py
pysf/errors.py
pysf/generalisation.py
pysf/logger.py
pysf/splits.py
pysf/utils.py
pysf/predictors/__init__.py
pysf/predictors/arima.py
pysf/predictors/baselines.py
pysf/predictors/fda.py
pysf/predictors/forest.py
pysf/predictors/framework.py
pysf/predictors/kernels.py
pysf/predictors/lstm.py
pysf/predictors/tuning.py
pysf/transformers/__init__.py
pysf/transformers/framework.py
pysf/transformers/smoothing.py
pysf-0.0.4.dist-info/METADATA
pysf-0.0.4.dist-info/RECORD
pysf-0.0.4.dist-info/WHEEL
pysf-0.0.4.dist-info/top_level.txt
