Metadata-Version: 2.1
Name: pysf
Version: 0.0.4
Summary: Supervised Forecasting
Home-page: https://github.com/ahmedgc/pysf
Author: Ahmed Guecioueur
Author-email: ucakaag@ucl.ac.uk
License: MIT
Platform: UNKNOWN
Classifier: Programming Language :: Python :: 3
Classifier: License :: OSI Approved :: MIT License
Classifier: Operating System :: OS Independent
